google_voice_takeout_parser/__init__.py
google_voice_takeout_parser/_version.py
google_voice_takeout_parser/google_voice_takeout_parser.py
google_voice_takeout_parser/py.typed
google_voice_takeout_parser/scripts/google_voice_parser.py
google_voice_takeout_parser-0.1.5.dist-info/METADATA
google_voice_takeout_parser-0.1.5.dist-info/WHEEL
google_voice_takeout_parser-0.1.5.dist-info/licenses/LICENSE
google_voice_takeout_parser-0.1.5.dist-info/RECORD
