Metadata-Version: 2.4
Name: google-voice-takeout-parser
Version: 0.1.5
Summary: Python package for parsing Google Voice takeout data.
Project-URL: Source, https://github.com/moshekaplan/google-voice-takeout-parser
Author-email: Moshe Kaplan <me@moshekaplan.com>
License: This is free and unencumbered software released into the public domain.
License-File: LICENSE
Requires-Python: <4,>=3.7
Requires-Dist: html5lib
